django_cdc/__init__.py
django_cdc/settings.py
django_cdc/management/__init__.py
django_cdc/management/commands/__init__.py
django_cdc/management/commands/setservice.py
django_cdc/models/__init__.py
django_cdc/models/constants.py
django_cdc/models/managers.py
django_cdc/models/patcher.py
django_cdc/models/services.py
django_cdc/models/tracker.py
django_cdc/tests/__init__.py
django_cdc/tests/runtests.py
django_cdc/tests/runtests_custom_auth.py
django_cdc/tests/urls.py
django_cdc/tests/audit_log_tests/__init__.py
django_cdc/tests/audit_log_tests/models.py
django_cdc/tests/audit_log_tests/test_logging.py
django_cdc/tests/audit_log_tests/test_manager.py
django_cdc/tests/audit_log_tests/views.py
django_cdc-2.0.11.dist-info/METADATA
django_cdc-2.0.11.dist-info/RECORD
django_cdc-2.0.11.dist-info/WHEEL
django_cdc-2.0.11.dist-info/top_level.txt
