Metadata-Version: 2.1
Name: django-cdc
Version: 2.0.11
Summary: CDC for django models
Home-page: https://bitbucket.org/DelhiveryTech/djangocdc/overview
Author: Delhivery
Author-email: noreply@delhivery.com
License: MIT
Download-URL: https://bitbucket.org/DelhiveryTech/djangocdc/get/v2.0.11.zip
Platform: UNKNOWN
Classifier: Development Status :: 5 - Production/Stable
Classifier: Environment :: Plugins
Classifier: Framework :: Django
Classifier: Intended Audience :: Developers
Classifier: License :: OSI Approved :: MIT License
Classifier: Topic :: Software Development :: Libraries :: Python Modules
Classifier: Programming Language :: Python
Classifier: Programming Language :: Python :: 2.6
Classifier: Programming Language :: Python :: 2.7
Classifier: Programming Language :: Python :: 3
Classifier: Programming Language :: Python :: 3.2
Classifier: Programming Language :: Python :: 3.3
Classifier: Programming Language :: Python :: 3.4
Requires-Dist: confluent-kafka
Requires-Dist: dill
Requires-Dist: pyyaml
Requires-Dist: enum34
Requires-Dist: django-extensions
Requires-Dist: django-bitfield
Requires-Dist: boto3
